routelit/__init__.py
routelit/assets_utils.py
routelit/builder.py
routelit/domain.py
routelit/exceptions.py
routelit/py.typed
routelit/routelit.py
routelit/static/routelit.svg
routelit/templates/index.html
routelit/utils/__init__.py
routelit/utils/async_to_sync_gen.py
routelit/utils/js_deps.py
routelit/utils/misc.py
routelit/utils/property_dict.py
routelit-0.6.0.dist-info/METADATA
routelit-0.6.0.dist-info/WHEEL
routelit-0.6.0.dist-info/licenses/LICENSE
routelit-0.6.0.dist-info/RECORD
