Metadata-Version: 2.4
Name: routelit
Version: 0.6.0
Summary: Project to build easy user interfaces, agnostic for http frameworks
Project-URL: Homepage, https://routelit.github.io/routelit/
Project-URL: Repository, https://github.com/routelit/routelit
Project-URL: Documentation, https://routelit.github.io/routelit/
Author-email: Rolando Gómez Tabar <rolangom@gmail.com>
License-File: LICENSE
Keywords: data analysis,data science,fastapi,flask,gradio,machine learning,numpy,pandas,python,shiny,streamlit
Classifier: Intended Audience :: Developers
Classifier: Intended Audience :: Science/Research
Classifier: Programming Language :: Python
Classifier: Programming Language :: Python :: 3
Classifier: Programming Language :: Python :: 3.9
Classifier: Programming Language :: Python :: 3.10
Classifier: Programming Language :: Python :: 3.11
Classifier: Programming Language :: Python :: 3.12
Classifier: Programming Language :: Python :: 3.13
Classifier: Topic :: Scientific/Engineering :: Artificial Intelligence
Classifier: Topic :: Scientific/Engineering :: Information Analysis
Classifier: Topic :: Software Development :: Libraries :: Python Modules
Requires-Python: <4.0,>=3.9
